screenplay_pdf_to_json/__init__.py
screenplay_pdf_to_json/convert.py
screenplay_pdf_to_json/parse_pdf/SortLines.py
screenplay_pdf_to_json/parse_pdf/__init__.py
screenplay_pdf_to_json/parse_pdf/cleanPage.py
screenplay_pdf_to_json/parse_pdf/getTopTrends.py
screenplay_pdf_to_json/parse_pdf/groupDualDialogues.py
screenplay_pdf_to_json/parse_pdf/groupLines.py
screenplay_pdf_to_json/parse_pdf/groupSections.py
screenplay_pdf_to_json/parse_pdf/processInitialPages.py
screenplay_pdf_to_json/parse_pdf/stitchSeperateWordsIntoLines.py
screenplay_pdf_to_json/utils/__init__.py
screenplay_pdf_to_json/utils/characterHelpers.py
screenplay_pdf_to_json/utils/cleanScript.py
screenplay_pdf_to_json/utils/headingHelpers.py
screenplay_pdf_to_json/utils/transitionHelpers.py
screenplay_pdf_to_json-0.3.4.dist-info/LICENSE.txt
screenplay_pdf_to_json-0.3.4.dist-info/WHEEL
screenplay_pdf_to_json-0.3.4.dist-info/METADATA
screenplay_pdf_to_json-0.3.4.dist-info/RECORD
